mau_html_visitor/__init__.py
mau_html_visitor/templates/block.html
mau_html_visitor/templates/block_group.html
mau_html_visitor/templates/callout.html
mau_html_visitor/templates/callouts_entry.html
mau_html_visitor/templates/container.html
mau_html_visitor/templates/content_image.html
mau_html_visitor/templates/document.html
mau_html_visitor/templates/footnote.html
mau_html_visitor/templates/footnotes.html
mau_html_visitor/templates/footnotes_entry.html
mau_html_visitor/templates/header.html
mau_html_visitor/templates/horizontal_rule.html
mau_html_visitor/templates/list.html
mau_html_visitor/templates/list_item.html
mau_html_visitor/templates/paragraph.html
mau_html_visitor/templates/raw.html
mau_html_visitor/templates/sentence.html
mau_html_visitor/templates/source.html
mau_html_visitor/templates/text.html
mau_html_visitor/templates/toc.html
mau_html_visitor/templates/toc_entry.html
mau_html_visitor/templates/verbatim.html
mau_html_visitor/templates/block/admonition.html
mau_html_visitor/templates/block/quote.html
mau_html_visitor/templates/macro/class.html
mau_html_visitor/templates/macro/header.html
mau_html_visitor/templates/macro/image.html
mau_html_visitor/templates/macro/link.html
mau_html_visitor/templates/style/caret.html
mau_html_visitor/templates/style/star.html
mau_html_visitor/templates/style/tilde.html
mau_html_visitor/templates/style/underscore.html
mau_html_visitor-2.0.2.dist-info/entry_points.txt
mau_html_visitor-2.0.2.dist-info/LICENSE
mau_html_visitor-2.0.2.dist-info/WHEEL
mau_html_visitor-2.0.2.dist-info/METADATA
mau_html_visitor-2.0.2.dist-info/RECORD
