Metadata-Version: 2.1
Name: mau_html_visitor
Version: 2.0.2
Summary: A visitor for Mau that converts the AST into HTML
Author-email: Leonardo Giordani <giordani.leonardo@gmail.com>
Requires-Python: >=3.7
Classifier: Development Status :: 5 - Production/Stable
Classifier: License :: OSI Approved :: MIT License
Classifier: Intended Audience :: Developers
Classifier: Operating System :: OS Independent
Classifier: Programming Language :: Python
Classifier: Programming Language :: Python :: 3
Classifier: Programming Language :: Python :: 3.7
Classifier: Programming Language :: Python :: 3.8
Classifier: Programming Language :: Python :: 3.9
Classifier: Programming Language :: Python :: 3.10
Classifier: Topic :: Software Development :: Libraries :: Python Modules
Requires-Dist: mau>=4.0.0,<5.0.0
Requires-Dist: pygments
Project-URL: Home, https://github.com/Project-Mau/mau-html-visitor
Provides-Extra: development
Provides-Extra: testing
